{
    "seed": 1,
    "startBlocksNum": 4,
    "blocksInLevel": ["blue","red"],
    "obstructionIdx": -1,
    "goal": {
        "score": 3000
    },
    "multiplier": {
        "decayTime": 2,
        "decayRate": 0.25,
        "max": 6
    },
    "spawn": {
        "timeMin": 2,
        "timeMax": 4,
        "timeDecreasePerTimeLimitPercent": 20,
        "timeDecreasePerTimeSeconds": 2,
        "timeDecreaseByTimePercent": 5
    },
    "block": {
        "speedMin": 4,
        "speedMax": 4,
        "speedIncreasePerTimeLimitPercent": 10,
        "speedIncreasePerTimeSeconds": 3,
        "speedIncreaseBySpeedPercent": 15
    },
    "starRewards": [
        3000,
        3000,
        3000
    ]
}